crimson/ast_dev_tool/__init__.py
crimson/ast_dev_tool/beta.py
crimson/ast_dev_tool/collector.py
crimson/ast_dev_tool/getter.py
crimson/ast_dev_tool/node_info.py
crimson/ast_dev_tool/printer.py
crimson/ast_dev_tool/util.py
crimson_ast_dev_tool-0.2.3.dist-info/LICENSE
crimson_ast_dev_tool-0.2.3.dist-info/METADATA
crimson_ast_dev_tool-0.2.3.dist-info/WHEEL
crimson_ast_dev_tool-0.2.3.dist-info/top_level.txt
crimson_ast_dev_tool-0.2.3.dist-info/RECORD
