Metadata-Version: 2.1
Name: crimson-ast-dev-tool
Version: 0.2.3
Summary: basic setups to use ast
Author-email: Sisung Kim <sisung.kim1@gmail.com>
Project-URL: Homepage, https://github.com/crimson206/ast-dev-tool
Project-URL: Bug Tracker, https://github.com/crimson206/ast-dev-tool/issues
Classifier: Programming Language :: Python :: 3
Classifier: Intended Audience :: Developers
Classifier: Topic :: Software Development :: Build Tools
Classifier: License :: OSI Approved :: MIT License
Classifier: Operating System :: OS Independent
Requires-Python: >=3.9
License-File: LICENSE
Requires-Dist: pydantic
